nonebot_plugin_saa/nonebug/__init__.py
nonebot_plugin_saa/nonebug/fixtures.py
nonebot_plugin_send_anything_anywhere_nonebug-0.1.0a0.dist-info/entry_points.txt
nonebot_plugin_send_anything_anywhere_nonebug-0.1.0a0.dist-info/WHEEL
nonebot_plugin_send_anything_anywhere_nonebug-0.1.0a0.dist-info/METADATA
nonebot_plugin_send_anything_anywhere_nonebug-0.1.0a0.dist-info/RECORD
