Metadata-Version: 2.1
Name: nonebot-plugin-send-anything-anywhere-nonebug
Version: 0.1.0a0
Summary: A nonebug helper for nonebot-plugin-send-anything-anything
Home-page: https://github.com/felinae98/nonebot-plugin-send-anything-anywhere-nonebug
License: MIT
Author: felinae98
Author-email: me@felinae98.cn
Requires-Python: >=3.10,<4.0
Classifier: Framework :: Pytest
Classifier: License :: OSI Approved :: MIT License
Classifier: Programming Language :: Python :: 3
Classifier: Programming Language :: Python :: 3.10
Classifier: Programming Language :: Python :: 3.11
Requires-Dist: nonebot-plugin-send-anything-anywhere (>=0.2.2,<0.3.0)
Requires-Dist: nonebug (>=0.3.1,<0.4.0)
Requires-Dist: pytest-mock (>=3.10.0,<4.0.0)
